shippo_mcp/__init__.py
shippo_mcp/server.py
shippo_mcp-0.1.2.dist-info/METADATA
shippo_mcp-0.1.2.dist-info/WHEEL
shippo_mcp-0.1.2.dist-info/entry_points.txt
shippo_mcp-0.1.2.dist-info/RECORD
