Metadata-Version: 2.4
Name: shippo-mcp
Version: 0.1.2
Summary: An unofficial MCP server for Shippo shipping API integration
Author: Foad Kesheh
License: MIT
Classifier: Programming Language :: Python :: 3
Classifier: Programming Language :: Python :: 3.9
Classifier: Programming Language :: Python :: 3.10
Classifier: Programming Language :: Python :: 3.11
Classifier: Programming Language :: Python :: 3.12
Classifier: Programming Language :: Python :: 3.13
Requires-Python: >=3.9
Requires-Dist: anyio>=4.5
Requires-Dist: click>=8.1.0
Requires-Dist: fastmcp>=2.10.5
Requires-Dist: mcp[cli]>=1.11.0
Requires-Dist: shippo>=3.9.0
